daily_digest/__init__.py
daily_digest/admin.py
daily_digest/apps.py
daily_digest/config.py
daily_digest/models.py
daily_digest/tests.py
daily_digest/urls.py
daily_digest/utils.py
daily_digest/views.py
daily_digest/management/__init__.py
daily_digest/management/commands/__init__.py
daily_digest/management/commands/send_daily_digest.py
daily_digest/migrations/__init__.py
daily_digest/templates/daily_digest/base.html
daily_digest/templates/daily_digest/email.html
leather/__init__.py
leather/axis.py
leather/chart.py
leather/data_types.py
leather/grid.py
leather/lattice.py
leather/svg.py
leather/testcase.py
leather/theme.py
leather/utils.py
leather/scales/__init__.py
leather/scales/base.py
leather/scales/linear.py
leather/scales/ordinal.py
leather/scales/temporal.py
leather/series/__init__.py
leather/series/base.py
leather/series/category.py
leather/shapes/__init__.py
leather/shapes/bars.py
leather/shapes/base.py
leather/shapes/columns.py
leather/shapes/dots.py
leather/shapes/line.py
leather/ticks/__init__.py
leather/ticks/base.py
leather/ticks/score.py
leather/ticks/score_time.py
project/__init__.py
project/settings.py
project/urls.py
project/wsgi.py
project/photos/__init__.py
project/photos/apps.py
project/photos/models.py
project/photos/migrations/0001_initial.py
project/photos/migrations/__init__.py
daily_digest-0.0.3.dist-info/LICENSE
daily_digest-0.0.3.dist-info/METADATA
daily_digest-0.0.3.dist-info/WHEEL
daily_digest-0.0.3.dist-info/top_level.txt
daily_digest-0.0.3.dist-info/RECORD
